siena/__init__.py
siena/__main__.py
siena/siena_cli.py
siena/core/__init__.py
siena/core/actions.py
siena/core/similarity.py
siena/server/__init__.py
siena/server/siena_server.py
siena/server/frontend/__init__.py
siena/server/frontend/error.html
siena/server/frontend/siena.html
siena/server/frontend/start.html
siena/server/frontend/assets/__init__.py
siena/server/frontend/images/__init__.py
siena/server/frontend/scripts/__init__.py
siena/server/frontend/scripts/iziToast.min.js
siena/server/frontend/scripts/session.js
siena/server/frontend/scripts/siena.js
siena/server/frontend/scripts/start.js
siena/server/frontend/styles/__init__.py
siena/server/frontend/styles/bootstrap.min.css
siena/server/frontend/styles/card.css
siena/server/frontend/styles/context_menu.css
siena/server/frontend/styles/input.css
siena/server/frontend/styles/iziToast.min.css
siena/server/frontend/styles/microsoft.css
siena/server/frontend/styles/scrollbar.css
siena/server/frontend/styles/siena.css
siena/server/frontend/styles/start.css
siena/server/siena_api/__init__.py
siena/server/siena_api/routes.py
siena/shared/__init__.py
siena/shared/constants.py
siena/shared/exceptions/__init__.py
siena/shared/exceptions/base.py
siena/shared/exceptions/cli.py
siena/shared/exceptions/core.py
siena/shared/exceptions/io.py
siena/shared/exceptions/server.py
siena/utils/__init__.py
siena/utils/io.py
siena/utils/siena_logging_formatter.py
siena-1.0.2.dist-info/LICENSE
siena-1.0.2.dist-info/METADATA
siena-1.0.2.dist-info/WHEEL
siena-1.0.2.dist-info/entry_points.txt
siena-1.0.2.dist-info/top_level.txt
siena-1.0.2.dist-info/RECORD
