Metadata-Version: 2.1
Name: siena
Version: 1.0.2
Summary: SIENA tool for efficient entity annotation.
Home-page: https://github.com/siena-nlp/siena
Author: Akalanka Sakalasooriya
Author-email: himesha@outlook.com
License: Apache License 2.0
Classifier: Development Status :: 3 - Alpha
Classifier: Framework :: Flask
Classifier: Intended Audience :: Developers
Classifier: Intended Audience :: Education
Classifier: Intended Audience :: Science/Research
Classifier: License :: OSI Approved :: Apache Software License
Classifier: Operating System :: OS Independent
Classifier: Programming Language :: Python :: 3
Classifier: Programming Language :: Python :: 3.7
Classifier: Programming Language :: Python :: 3.8
License-File: LICENSE
Requires-Dist: beautifulsoup4 (==4.11.1)
Requires-Dist: flask (>=2.1.2)
Requires-Dist: Flask-Cors (==3.0.10)
Requires-Dist: Flask-WTF (==1.0.1)
Requires-Dist: nltk (==3.6.3)
Requires-Dist: pandas (==1.4.3)
Requires-Dist: waitress (>=2.1.2)
Requires-Dist: rasa (~=2.8.8)
Requires-Dist: ruamel.yaml (<0.17.0,>=0.16.5)
